sgp_agents/__init__.py
sgp_agents/_base_client.py
sgp_agents/_client.py
sgp_agents/_compat.py
sgp_agents/_constants.py
sgp_agents/_exceptions.py
sgp_agents/_files.py
sgp_agents/_models.py
sgp_agents/_qs.py
sgp_agents/_resource.py
sgp_agents/_response.py
sgp_agents/_streaming.py
sgp_agents/_types.py
sgp_agents/_version.py
sgp_agents/py.typed
sgp_agents/_utils/__init__.py
sgp_agents/_utils/_logs.py
sgp_agents/_utils/_proxy.py
sgp_agents/_utils/_reflection.py
sgp_agents/_utils/_streams.py
sgp_agents/_utils/_sync.py
sgp_agents/_utils/_transform.py
sgp_agents/_utils/_typing.py
sgp_agents/_utils/_utils.py
sgp_agents/lib/.keep
sgp_agents/resources/__init__.py
sgp_agents/resources/configs.py
sgp_agents/resources/health.py
sgp_agents/resources/healthz.py
sgp_agents/types/__init__.py
sgp_agents/types/compound_condition_input_param.py
sgp_agents/types/compound_condition_output.py
sgp_agents/types/config_create_params.py
sgp_agents/types/config_create_response.py
sgp_agents/types/config_delete_response.py
sgp_agents/types/config_execute_params.py
sgp_agents/types/config_list_params.py
sgp_agents/types/config_list_response.py
sgp_agents/types/config_retrieve_response.py
sgp_agents/types/jinja_node_template.py
sgp_agents/types/jinja_node_template_param.py
sgp_agents/types/node_item_input_param.py
sgp_agents/types/node_item_output.py
sgp_agents/types/parameter_type_input_param.py
sgp_agents/types/parameter_type_output.py
sgp_agents/types/plan_config_input_param.py
sgp_agents/types/plan_config_output.py
sgp_agents/types/unary_condition.py
sgp_agents/types/unary_condition_param.py
sgp_agents/types/workflow_config_input_param.py
sgp_agents/types/workflow_config_output.py
sgp_agents/types/workflow_item.py
sgp_agents/types/workflow_item_param.py
scale_gp_agents-0.1.0a8.dist-info/METADATA
scale_gp_agents-0.1.0a8.dist-info/WHEEL
scale_gp_agents-0.1.0a8.dist-info/licenses/LICENSE
scale_gp_agents-0.1.0a8.dist-info/RECORD
